[
  {
    "lang": "ar",
    "total": 251,
    "translated": 251,
    "missing_count": 0,
    "missing_keys": []
  },
  {
    "lang": "de",
    "total": 251,
    "translated": 251,
    "missing_count": 0,
    "missing_keys": []
  },
  {
    "lang": "es",
    "total": 251,
    "translated": 251,
    "missing_count": 0,
    "missing_keys": []
  },
  {
    "lang": "fr",
    "total": 251,
    "translated": 251,
    "missing_count": 0,
    "missing_keys": []
  },
  {
    "lang": "hi",
    "total": 251,
    "translated": 251,
    "missing_count": 0,
    "missing_keys": []
  },
  {
    "lang": "in",
    "total": 251,
    "translated": 251,
    "missing_count": 0,
    "missing_keys": []
  },
  {
    "lang": "it",
    "total": 251,
    "translated": 251,
    "missing_count": 0,
    "missing_keys": []
  },
  {
    "lang": "ja",
    "total": 251,
    "translated": 251,
    "missing_count": 0,
    "missing_keys": []
  },
  {
    "lang": "ko",
    "total": 251,
    "translated": 251,
    "missing_count": 0,
    "missing_keys": []
  },
  {
    "lang": "pl",
    "total": 251,
    "translated": 251,
    "missing_count": 0,
    "missing_keys": []
  },
  {
    "lang": "pt-rBR",
    "total": 251,
    "translated": 251,
    "missing_count": 0,
    "missing_keys": []
  },
  {
    "lang": "th",
    "total": 251,
    "translated": 251,
    "missing_count": 0,
    "missing_keys": []
  },
  {
    "lang": "tr",
    "total": 251,
    "translated": 251,
    "missing_count": 0,
    "missing_keys": []
  },
  {
    "lang": "vi",
    "total": 251,
    "translated": 251,
    "missing_count": 0,
    "missing_keys": []
  },
  {
    "lang": "zh-rCN",
    "total": 251,
    "translated": 251,
    "missing_count": 0,
    "missing_keys": []
  },
  {
    "lang": "zh-rTW",
    "total": 251,
    "translated": 251,
    "missing_count": 0,
    "missing_keys": []
  }
]

